simpler_sf/__init__.py
simpler_sf/_simpler_sf.py
simpler_sf-1.0.4.dist-info/LICENSE
simpler_sf-1.0.4.dist-info/METADATA
simpler_sf-1.0.4.dist-info/WHEEL
simpler_sf-1.0.4.dist-info/top_level.txt
simpler_sf-1.0.4.dist-info/RECORD
