Metadata-Version: 2.1
Name: simpler_sf
Version: 1.0.4
Summary: Extending Simple Salesforce to support Pandas exports and more.
Home-page: https://github.com/benvigano/simpler-sf
Author: benvigano
Author-email: beniamino.vigano@protonmail.com
License: MIT
Keywords: Salesforce,Simple Salesforce,Pandas,Dataframe,Unpack Salesforce
License-File: LICENSE
